Workbook
Name aporte: 'APP IMOBI INVEST'!$D$22
Name patrimonio: 'APP IMOBI INVEST'!$D$25
Name qtde_anos: 'APP IMOBI INVEST'!$D$23
Name rendimento_carteira: 'APP IMOBI INVEST'!$D$18
Name salario: 'APP IMOBI INVEST'!$D$17
Name sugetao_investimento: 'APP IMOBI INVEST'!$D$19
Name taxa_mensal: 'APP IMOBI INVEST'!$D$24

Sheet APP IMOBI INVEST
B16: CONFIGURAÇÕES
B17: Salário | D17: 4000
B18: Rendimento Carteira | D18: 0.01
B19: Sugestão de Investimento | D19: =D17*30% -> 1200
B21: INVESTIMENTO MENSAL
B22: Quanto investir por mês ? | D22: 100
B23: Por Quantos Anos ? | D23: 1
B24: Taxa de Rendimento mensal ? | D24: 0.0102
A25: 2 | B25: Patrimônio acumulado ? | D25: =FV(taxa_mensal,qtde_anos*12,aporte*-1) -> 1269.6623
A26: 5 | B26: Dividendos Mensais ? | D26: =patrimonio*rendimento_carteira -> 12.696623
A27: 10
A28: 20 | B28: CENÁRIOS | D28: DIVIDENDO
A29: 30 | B29: Quantos em 2 anos ? | C29: =FV($D$24,$A25*12,$D$22*-1) -> 2703.7529 | D29: =C29*rendimento_carteira -> 27.037529
B30: Quantos em 5 anos ? | C30: =FV($D$24,$A26*12,$D$22*-1) -> 8219.6842 | D30: =C30*rendimento_carteira -> 82.196842
B31: Quantos em 10 anos ? | C31: =FV($D$24,$A27*12,$D$22*-1) -> 23330.816 | D31: =C31*rendimento_carteira -> 233.30816
B32: Quantos em 20 anos ? | C32: =FV($D$24,$A28*12,$D$22*-1) -> 102182.98 | D32: =C32*rendimento_carteira -> 1021.8298
B33: Quantos em 30 anos ? | C33: =FV($D$24,$A29*12,$D$22*-1) -> 368683.05 | D33: =C33*rendimento_carteira -> 3686.8305
B37: PERFIL | C37: Conservador
B38: Valor a ser investido por mês | C38: =aporte -> 100
B40: TIPO DE FII | C40: Percentual Sugerido | D40: Valores
B41: PAPEL | C41: =VLOOKUP($C$37&"-"&B41,TABELA!$A:$D,4,FALSE) -> 0.3 | D41: =C41*$C$38 -> 30
B42: TIJOLO | C42: =VLOOKUP($C$37&"-"&B42,TABELA!$A:$D,4,FALSE) -> 0.5 | D42: =C42*$C$38 -> 50
B43: HÍBRIDOS | C43: =VLOOKUP($C$37&"-"&B43,TABELA!$A:$D,4,FALSE) -> 0.1 | D43: =C43*$C$38 -> 10
B44: FOFs | C44: =VLOOKUP($C$37&"-"&B44,TABELA!$A:$D,4,FALSE) -> 0.1 | D44: =C44*$C$38 -> 10
B45: DESENVOLVIMENTO | C45: =VLOOKUP($C$37&"-"&B45,TABELA!$A:$D,4,FALSE) -> 0 | D45: =C45*$C$38 -> 0
B46: HOTELARIAS | C46: =VLOOKUP($C$37&"-"&B46,TABELA!$A:$D,4,FALSE) -> 0 | D46: =C46*$C$38 -> 0
D47: =SUM(D41:D46) -> 100

Sheet TABELA
A2: CHAVE | B2: PERFIL | C2: TIPO DE FII | D2: %
A3: =B3&"-"&C3 -> Conservador-PAPEL | B3: Conservador | C3: PAPEL | D3: 0.3
A4: =B4&"-"&C4 -> Conservador-TIJOLO | B4: Conservador | C4: TIJOLO | D4: 0.5 | I4: %
A5: =B5&"-"&C5 -> Conservador-HÍBRIDOS | B5: Conservador | C5: HÍBRIDOS | D5: 0.1 | H5: Moderado-TIJOLO | I5: =VLOOKUP(H5,$A:$D,4,FALSE) -> 0.43
A6: =B6&"-"&C6 -> Conservador-FOFs | B6: Conservador | C6: FOFs | D6: 0.1
A7: =B7&"-"&C7 -> Conservador-DESENVOLVIMENTO | B7: Conservador | C7: DESENVOLVIMENTO | D7: 0
A8: =B8&"-"&C8 -> Conservador-HOTELARIAS | B8: Conservador | C8: HOTELARIAS | D8: 0
A9: =B9&"-"&C9 -> Moderado-PAPEL | B9: Moderado | C9: PAPEL | D9: 0.32
A10: =B10&"-"&C10 -> Moderado-TIJOLO | B10: Moderado | C10: TIJOLO | D10: 0.43
A11: =B11&"-"&C11 -> Moderado-HÍBRIDOS | B11: Moderado | C11: HÍBRIDOS | D11: 0.08
A12: =B12&"-"&C12 -> Moderado-FOFs | B12: Moderado | C12: FOFs | D12: 0.1
A13: =B13&"-"&C13 -> Moderado-DESENVOLVIMENTO | B13: Moderado | C13: DESENVOLVIMENTO | D13: 0.05
A14: =B14&"-"&C14 -> Moderado-HOTELARIAS | B14: Moderado | C14: HOTELARIAS | D14: 0.02
A15: =B15&"-"&C15 -> Agressivo-PAPEL | B15: Agressivo | C15: PAPEL | D15: 0.5
A16: =B16&"-"&C16 -> Agressivo-TIJOLO | B16: Agressivo | C16: TIJOLO | D16: 0.2
A17: =B17&"-"&C17 -> Agressivo-HÍBRIDOS | B17: Agressivo | C17: HÍBRIDOS | D17: 0.15
... A20: =B20&"-"&C20 -> Agressivo-HOTELARIAS | B20: Agressivo | C20: HOTELARIAS | D20: 0.05
